{
  "variants": {
    "facing=north,lit=false": {
      "model": "cuboidmod:block/refined_inscriber"
    },
    "facing=east,lit=false": {
      "model": "cuboidmod:block/refined_inscriber",
      "y": 90
    },
    "facing=south,lit=false": {
      "model": "cuboidmod:block/refined_inscriber",
      "y": 180
    },
    "facing=west,lit=false": {
      "model": "cuboidmod:block/refined_inscriber",
      "y": 270
    },
    "facing=north,lit=true": {
      "model": "cuboidmod:block/refined_inscriber_lit"
    },
    "facing=east,lit=true": {
      "model": "cuboidmod:block/refined_inscriber_lit",
      "y": 90
    },
    "facing=south,lit=true": {
      "model": "cuboidmod:block/refined_inscriber_lit",
      "y": 180
    },
    "facing=west,lit=true": {
      "model": "cuboidmod:block/refined_inscriber_lit",
      "y": 270
    }
  }
}
